api/__init__.py
api/app.py
api/core/__init__.py
api/core/utils.py
api/routers/__init__.py
api/routers/v1.py
api/schemas/schemas.py
wemulate_api-2.0.2.dist-info/entry_points.txt
wemulate_api-2.0.2.dist-info/LICENSE
wemulate_api-2.0.2.dist-info/WHEEL
wemulate_api-2.0.2.dist-info/METADATA
wemulate_api-2.0.2.dist-info/RECORD
